main.py
automlex-0.0.1.dist-info/LICENSE
automlex-0.0.1.dist-info/METADATA
automlex-0.0.1.dist-info/WHEEL
automlex-0.0.1.dist-info/top_level.txt
automlex-0.0.1.dist-info/RECORD
